query_exporter/__init__.py
query_exporter/config.py
query_exporter/db.py
query_exporter/executor.py
query_exporter/main.py
query_exporter/metrics.py
query_exporter/periodic_call.py
query_exporter/py.typed
query_exporter/schema.py
query_exporter/yaml.py
query_exporter-4.0.1.dist-info/licenses/LICENSE.txt
query_exporter-4.0.1.dist-info/METADATA
query_exporter-4.0.1.dist-info/WHEEL
query_exporter-4.0.1.dist-info/entry_points.txt
query_exporter-4.0.1.dist-info/top_level.txt
query_exporter-4.0.1.dist-info/RECORD
