Metadata-Version: 2.4
Name: query-exporter
Version: 4.0.1
Summary: Export Prometheus metrics generated from SQL queries
Author-email: Alberto Donato <alberto.donato@gmail.com>
Maintainer-email: Alberto Donato <alberto.donato@gmail.com>
License-Expression: GPL-3.0-or-later
Project-URL: Changelog, https://github.com/albertodonato/query-exporter/blob/main/CHANGES.rst
Project-URL: Documentation, https://github.com/albertodonato/query-exporter
Project-URL: Homepage, https://github.com/albertodonato/query-exporter
Project-URL: Issue Tracker, https://github.com/albertodonato/query-exporter/issues
Project-URL: Release Notes, https://github.com/albertodonato/query-exporter/blob/main/CHANGES.rst
Project-URL: Source Code, https://github.com/albertodonato/query-exporter
Keywords: exporter,metric,prometheus,sql
Classifier: Development Status :: 5 - Production/Stable
Classifier: Framework :: AsyncIO
Classifier: Intended Audience :: System Administrators
Classifier: Operating System :: OS Independent
Classifier: Programming Language :: Python :: 3 :: Only
Classifier: Programming Language :: Python :: 3.11
Classifier: Programming Language :: Python :: 3.12
Classifier: Programming Language :: Python :: 3.13
Classifier: Programming Language :: Python :: 3.14
Classifier: Topic :: Database
Classifier: Topic :: System :: Monitoring
Classifier: Topic :: Utilities
Requires-Python: >=3.11
License-File: LICENSE.txt
Requires-Dist: aiohttp
Requires-Dist: croniter
Requires-Dist: prometheus-aioexporter>=3.1
Requires-Dist: prometheus-client
Requires-Dist: pydantic
Requires-Dist: python-dateutil
Requires-Dist: pyyaml
Requires-Dist: sqlalchemy>=2
Requires-Dist: structlog
Provides-Extra: dbs
Requires-Dist: mysqlclient; extra == "dbs"
Requires-Dist: oracledb; extra == "dbs"
Requires-Dist: psycopg2-binary; extra == "dbs"
Requires-Dist: pymssql; extra == "dbs"
Provides-Extra: integration-tests
Requires-Dist: pytest; extra == "integration-tests"
Requires-Dist: pytest-asyncio; extra == "integration-tests"
Requires-Dist: pytest-docker; extra == "integration-tests"
Requires-Dist: query-exporter[dbs]; extra == "integration-tests"
Requires-Dist: requests; extra == "integration-tests"
Provides-Extra: testing
Requires-Dist: pytest; extra == "testing"
Requires-Dist: pytest-asyncio; extra == "testing"
Requires-Dist: pytest-mock; extra == "testing"
Requires-Dist: pytest-structlog; extra == "testing"
Dynamic: license-file
